helpers/__init__.py
helpers/gpr/__init__.py
helpers/gpr/gpr.py
helpers/gpr/interactive.py
helpers/gpr/plot.py
helpers/gpr/training.py
helpers/gpr/types.py
helpers/gpr/updater.py
helpers/ilc/__init__.py
helpers/ilc/animate.py
helpers/ilc/ilc.py
helpers/ilc/plot.py
helpers/ilc/system.py
helpers/maths/__init__.py
helpers/maths/latex.py
helpers/maths/linear.py
helpers/maths/matrix.py
helpers/maths/solver.py
helpers/maths/types.py
helpers/motor/__init__.py
helpers/motor/control.py
helpers/motor/features.py
helpers/motor/motor.py
helpers/motor/plot.py
helpers/motor/simulation.py
helpers/motor/temperature.py
helpers/motor/types.py
helpers/network/__init__.py
helpers/network/data.py
helpers/network/info.py
helpers/network/scaler.py
helpers/network/serialize.py
helpers/network/training.py
helpers/network/visualize.py
helpers/rl/__init__.py
helpers/rl/animate.py
helpers/rl/app.py
helpers/rl/chance.py
helpers/rl/game.py
helpers/rl/learn.py
helpers/rl/table.py
helpers/robot/__init__.py
helpers/robot/animation.py
helpers/robot/arm.py
helpers/robot/control/__init__.py
helpers/robot/control/control.py
helpers/robot/control/joint_space.py
helpers/robot/control/task_space.py
helpers/robot/control/trajectories.py
helpers/robot/inverse.py
helpers/robot/jacobian.py
helpers/robot/joint.py
helpers/robot/link.py
helpers/robot/planar/__init__.py
helpers/robot/planar/animation.py
helpers/robot/planar/arm.py
helpers/robot/planar/dynamics.py
helpers/robot/predict.py
helpers/robot/simulate/__init__.py
helpers/robot/simulate/common.py
helpers/robot/simulate/measurement.py
helpers/robot/simulate/results.py
helpers/robot/simulate/simulate.py
helpers/robot/simulate/solver.py
helpers/robot/simulate/types.py
helpers/robot/system.py
helpers/tank/__init__.py
helpers/tank/animation.py
helpers/tank/control.py
helpers/tank/discretize.py
helpers/tank/dynamics.py
helpers/tank/geometry.py
helpers/tank/learn.py
helpers/tank/policy.py
helpers/tank/simulate.py
helpers/tank/state.py
helpers/tank/tank.py
mlcs_assignments-0.5.0.dist-info/LICENSE
mlcs_assignments-0.5.0.dist-info/METADATA
mlcs_assignments-0.5.0.dist-info/WHEEL
mlcs_assignments-0.5.0.dist-info/RECORD
